digital_nondigital_pdf_extraction/__init__.py
digital_nondigital_pdf_extraction/pdf_extractor.py
digital_nondigital_pdf_extraction-1.0.3.dist-info/METADATA
digital_nondigital_pdf_extraction-1.0.3.dist-info/WHEEL
digital_nondigital_pdf_extraction-1.0.3.dist-info/top_level.txt
digital_nondigital_pdf_extraction-1.0.3.dist-info/RECORD
